Metadata-Version: 2.1
Name: example-pkg-trdlo
Version: 0.1.1
Summary: Example package based on packaging python tutorials
Home-page: https://gitlab.com/avnovoselov/python-package-example
Author: Anatoliy Novoselov
Author-email: avnovoselov@gmail.com
License: UNKNOWN
Platform: UNKNOWN
Classifier: Programming Language :: Python :: 3
Classifier: License :: OSI Approved :: MIT License
Classifier: Operating System :: OS Independent
Requires-Python: >=3.8
